excel_serializer/__init__.py
excel_serializer/__main__.py
excel_serializer/decoder.py
excel_serializer/defaults.py
excel_serializer/encoder.py
excel_serializer-1.1.4.dist-info/licenses/LICENSE
excel_serializer-1.1.4.dist-info/METADATA
excel_serializer-1.1.4.dist-info/WHEEL
excel_serializer-1.1.4.dist-info/entry_points.txt
excel_serializer-1.1.4.dist-info/top_level.txt
excel_serializer-1.1.4.dist-info/RECORD
