Metadata-Version: 2.4
Name: excel-serializer
Version: 1.1.4
Summary: Dump/Load Excel files to/from Python objects
Author-email: Alexandre 'Tsu' Manuel <tsu@sulvia.fr>
License: MIT License
Project-URL: Homepage, https://github.com/alexandre-tsu-manuel/excel-serializer
Keywords: excel,xlsx,serializer,deserializer,dump,load
Classifier: License :: OSI Approved :: MIT License
Classifier: Programming Language :: Python
Classifier: Programming Language :: Python :: 3
Requires-Python: >=3.9
License-File: LICENSE
Requires-Dist: openpyxl
Provides-Extra: dev
Requires-Dist: black; extra == "dev"
Requires-Dist: bumpver; extra == "dev"
Requires-Dist: isort; extra == "dev"
Requires-Dist: pip-tools; extra == "dev"
Requires-Dist: pytest; extra == "dev"
Dynamic: license-file
